multiqc_dumpling/__init__.py
multiqc_dumpling/dumpling_intialization.py
multiqc_dumpling/__pycache__/__init__.cpython-311.pyc
multiqc_dumpling/__pycache__/__init__.cpython-313.pyc
multiqc_dumpling/__pycache__/dumpling_intialization.cpython-311.pyc
multiqc_dumpling/__pycache__/dumpling_intialization.cpython-313.pyc
multiqc_dumpling/modules/__init__.py
multiqc_dumpling/modules/__pycache__/__init__.cpython-311.pyc
multiqc_dumpling/modules/__pycache__/__init__.cpython-313.pyc
multiqc_dumpling/modules/dumpling/__init__.py
multiqc_dumpling/modules/dumpling/dumpling.py
multiqc_dumpling/modules/dumpling/__pycache__/__init__.cpython-311.pyc
multiqc_dumpling/modules/dumpling/__pycache__/__init__.cpython-313.pyc
multiqc_dumpling/modules/dumpling/__pycache__/dumpling.cpython-311.pyc
multiqc_dumpling/modules/dumpling/__pycache__/dumpling.cpython-313.pyc
multiqc_dumpling-0.3.dist-info/LICENSE
multiqc_dumpling-0.3.dist-info/METADATA
multiqc_dumpling-0.3.dist-info/WHEEL
multiqc_dumpling-0.3.dist-info/entry_points.txt
multiqc_dumpling-0.3.dist-info/top_level.txt
multiqc_dumpling-0.3.dist-info/RECORD
