Metadata-Version: 2.1
Name: multiqc_dumpling
Version: 0.3
Summary: MultiQC plugin for Dumpling DMS pipeline
Home-page: https://github.com/odcambc/MultiQC_dumpling
Download-URL: https://github.com/odcambc/MultiQC_dumpling/releases
Author: Christian Macdonald
Author-email: christian.macdonald@ucsf.edu
License: MIT
Keywords: bioinformatics
Classifier: Development Status :: 4 - Beta
Classifier: Environment :: Console
Classifier: Environment :: Web Environment
Classifier: Intended Audience :: Science/Research
Classifier: License :: OSI Approved :: MIT License
Classifier: Natural Language :: English
Classifier: Operating System :: MacOS :: MacOS X
Classifier: Operating System :: POSIX
Classifier: Operating System :: Unix
Classifier: Programming Language :: Python
Classifier: Programming Language :: JavaScript
Classifier: Topic :: Scientific/Engineering
Classifier: Topic :: Scientific/Engineering :: Bio-Informatics
License-File: LICENSE
Requires-Dist: multiqc>=1.0
Requires-Dist: pandas
